client/__init__.py
client/client.py
client/start_clients_mac.py
client/client/__init__.py
client/client/add_contact.py
client/client/database.py
client/client/del_contact.py
client/client/main_window.py
client/client/main_window_conv.py
client/client/start_dialog.py
client/client/transport.py
client/client/key/__init__.py
client/common/__init__.py
client/common/decos.py
client/common/descryptors.py
client/common/errors.py
client/common/metaclasses.py
client/common/utils.py
client/common/variables.py
client/doc/__init__.py
client/doc/source/__init__.py
client/doc/source/conf.py
client/logs/__init__.py
client/logs/config_client_log.py
client/logs/config_server_log.py
py_mess_client_kuznetsov-0.0.12.data/scripts/client_run
py_mess_client_kuznetsov-0.0.12.dist-info/METADATA
py_mess_client_kuznetsov-0.0.12.dist-info/WHEEL
py_mess_client_kuznetsov-0.0.12.dist-info/top_level.txt
py_mess_client_kuznetsov-0.0.12.dist-info/RECORD
