Metadata-Version: 2.1
Name: py-mess-client-kuznetsov
Version: 0.0.12
Summary: Mess Client
Home-page: UNKNOWN
Author: Sergey Kuznetsov
Author-email: ksn1974@mail.ru
License: UNKNOWN
Platform: UNKNOWN
Requires-Dist: PyQt5
Requires-Dist: sqlalchemy
Requires-Dist: pycryptodome
Requires-Dist: pycryptodomex
